spritegen
