Metadata-Version: 2.1
Name: LUASprites
Version: 0.0.22
Summary: Generate spritesheets and lua modules for easy image reference
Home-page: https://github.com/AJSteinhauser/LUASprites
Author: AJ Steinhauser
Author-email: ajsteinhauser11@gmail.com
License: MIT License
Classifier: Programming Language :: Python :: 3.8
Classifier: Operating System :: OS Independent
Requires-Python: >=3.7
License-File: LICENSE.txt
